pymeteo/__init__.py
pymeteo/constants.py
pymeteo/dynamics.py
pymeteo/interp.py
pymeteo/radar.py
pymeteo/skewt.py
pymeteo/thermo.py
pymeteo/uwyo.py
pymeteo/wrf.py
pymeteo/UI/acars.py
pymeteo/cm1/MainInterface.py
pymeteo/cm1/OptionsWidget.py
pymeteo/cm1/PlotWidget.py
pymeteo/cm1/StatWidget.py
pymeteo/cm1/__init__.py
pymeteo/cm1/read_grads.py
pymeteo/cm1/read_hdf5.py
pymeteo/cm1/hodographs/__init__.py
pymeteo/cm1/hodographs/curved90.py
pymeteo/cm1/hodographs/semicircle.py
pymeteo/cm1/hodographs/sickle.py
pymeteo/cm1/hodographs/straight.py
pymeteo/cm1/hodographs/straightllws.py
pymeteo/cm1/soundings/WK82.py
pymeteo/cm1/soundings/__init__.py
pymeteo/data/acars.py
pymeteo/data/airport_info.dat
pymeteo-1.0.3.data/scripts/cm1_geninit
pymeteo-1.0.3.data/scripts/plot-acars
pymeteo-1.0.3.data/scripts/skewt
pymeteo-1.0.3.data/scripts/skewt-blank
pymeteo-1.0.3.data/scripts/skewt-hdf
pymeteo-1.0.3.data/scripts/skewt-wrf
pymeteo-1.0.3.dist-info/LICENSE
pymeteo-1.0.3.dist-info/METADATA
pymeteo-1.0.3.dist-info/WHEEL
pymeteo-1.0.3.dist-info/top_level.txt
pymeteo-1.0.3.dist-info/RECORD
