Metadata-Version: 2.1
Name: pymeteo
Version: 1.0.3
Summary: Meteorology utilities, SkewT plotting and more
Home-page: https://wxster.com/projects/pymeteo
Author: Casey Webster
Author-email: casey.webster@gmail.com
Maintainer: Casey Webster
Maintainer-email: casey.webster@gmail.com
License: BSD 3-clause
Platform: any
Classifier: Intended Audience :: Science/Research
Classifier: License :: OSI Approved :: BSD License
Classifier: Topic :: Scientific/Engineering :: Atmospheric Science
Classifier: Development Status :: 5 - Production/Stable
Classifier: Topic :: Software Development :: Libraries :: Python Modules
Classifier: Programming Language :: Python :: 3
Classifier: Programming Language :: Python :: 3.10
License-File: LICENSE
